{
  "project_info": {
    "project_number": "1046726338655",
    "project_id": "nutrikmais",
    "storage_bucket": "nutrikmais.firebasestorage.app"
  },
  "client": [
    {
      "client_info": {
        "mobilesdk_app_id": "1:1046726338655:android:3f0c59edc7ad2fc9a853ea",
        "android_client_info": {
          "package_name": "com.nutrikmais"
        }
      },
      "oauth_client": [],
      "api_key": [
        {
          "current_key": "AIzaSyDkXW0qiNq0wjUaYjJMVQHmKHQRXuffQao"
        }
      ],
      "services": {
        "appinvite_service": {
          "other_platform_oauth_client": []
        }
      }
    },
    {
      "client_info": {
        "mobilesdk_app_id": "1:1046726338655:android:8de004f0ca7a591ea853ea",
        "android_client_info": {
          "package_name": "com.nutrikmais.nutrikmais"
        }
      },
      "oauth_client": [],
      "api_key": [
        {
          "current_key": "AIzaSyDkXW0qiNq0wjUaYjJMVQHmKHQRXuffQao"
        }
      ],
      "services": {
        "appinvite_service": {
          "other_platform_oauth_client": []
        }
      }
    }
  ],
  "configuration_version": "1"
}